pypiqe/__init__.py
pypiqe/piqe.py
pypiqe-1.2.dist-info/LICENSE
pypiqe-1.2.dist-info/METADATA
pypiqe-1.2.dist-info/WHEEL
pypiqe-1.2.dist-info/top_level.txt
pypiqe-1.2.dist-info/RECORD
