Metadata-Version: 2.1
Name: pypiqe
Version: 1.2
Summary: A python version of Matlab's Perception based Image Quality Evaluator (PIQE) no-reference image quality score
Home-page: https://github.com/michael-rutherford/pypiqe
Author: Michael W. Rutherford
Author-email: sykiemikey@hotmail.com
Classifier: License :: OSI Approved :: MIT License
Classifier: Programming Language :: Python :: 3
Classifier: Programming Language :: Python :: 3.10
License-File: LICENSE
Requires-Dist: numpy >=1.25.0
Requires-Dist: opencv-python >=4.7.0.72
